odoo/addons/mandate_partner_bank_creation/__init__.py
odoo/addons/mandate_partner_bank_creation/__manifest__.py
odoo/addons/mandate_partner_bank_creation/listeners/__init__.py
odoo/addons/mandate_partner_bank_creation/listeners/partner_bank_listener.py
odoo12_addon_mandate_partner_bank_creation-12.0.1.0.1.dist-info/METADATA
odoo12_addon_mandate_partner_bank_creation-12.0.1.0.1.dist-info/WHEEL
odoo12_addon_mandate_partner_bank_creation-12.0.1.0.1.dist-info/top_level.txt
odoo12_addon_mandate_partner_bank_creation-12.0.1.0.1.dist-info/RECORD
